excelstyleskit/__init__.py
excelstyleskit/excel/__init__.py
excelstyleskit/excel/excel.py
excelstyleskit/excel/styles.py
excelstyleskit/table/__init__.py
excelstyleskit/table/cell.py
excelstyleskit/table/table.py
excelstyleskit/test/__init__.py
excelstyleskit/test/cell.py
excelstyleskit/test/excel.py
excelstyleskit/test/table.py
excelstyleskit/utils/__init__.py
excelstyleskit/utils/verify.py
excelstyleskit-0.0.3.dist-info/METADATA
excelstyleskit-0.0.3.dist-info/WHEEL
excelstyleskit-0.0.3.dist-info/licenses/LICENSE
excelstyleskit-0.0.3.dist-info/RECORD
