Metadata-Version: 2.4
Name: excelstyleskit
Version: 0.0.3
Summary: A library to create excel styles
Project-URL: Repository, https://github.com/xanv754/ExcelStylesKit
Project-URL: Documentation, https://github.com/xanv754/ExcelStylesKit/blob/main/documentation.md
Project-URL: Issues, https://github.com/xanv754/ExcelStylesKit/issues
Project-URL: Changelog, https://github.com/xanv754/ExcelStylesKit/blob/main/CHANGELOG.md
Author-email: Angyee <angyeemarin.dev@gmail.com>
License: MIT License
License-File: LICENSE
Keywords: excel,openpyxl,styles
Classifier: License :: OSI Approved :: MIT License
Classifier: Operating System :: OS Independent
Classifier: Programming Language :: Python :: 3
Requires-Python: >=3.8
Requires-Dist: et-xmlfile>=1.1.0
Requires-Dist: openpyxl>=3.1.5
